git_pypi/__about__.py
git_pypi/__init__.py
git_pypi/builder.py
git_pypi/cmd.py
git_pypi/config.py
git_pypi/exc.py
git_pypi/git.py
git_pypi/types.py
git_pypi/cli/__init__.py
git_pypi/cli/configure.py
git_pypi/cli/run.py
git_pypi/package_index/__init__.py
git_pypi/package_index/base.py
git_pypi/package_index/combined.py
git_pypi/package_index/factory.py
git_pypi/package_index/git.py
git_pypi/package_index/localfs.py
git_pypi/web/__init__.py
git_pypi/web/app.py
git_pypi/web/server.py
git_pypi-1.1.0.dist-info/METADATA
git_pypi-1.1.0.dist-info/WHEEL
git_pypi-1.1.0.dist-info/entry_points.txt
git_pypi-1.1.0.dist-info/licenses/LICENSE.txt
git_pypi-1.1.0.dist-info/RECORD
