Metadata-Version: 2.4
Name: git-pypi
Version: 1.1.0
Project-URL: Documentation, https://github.com/pierec/git-pypi#readme
Project-URL: Issues, https://github.com/pierec/git-pypi/issues
Project-URL: Source, https://github.com/pierec/git-pypi
Author-email: pierec <pdettlaff@gmail.com>
License-Expression: MIT
License-File: LICENSE.txt
Classifier: Development Status :: 4 - Beta
Classifier: Programming Language :: Python
Classifier: Programming Language :: Python :: 3.10
Classifier: Programming Language :: Python :: 3.11
Classifier: Programming Language :: Python :: 3.12
Classifier: Programming Language :: Python :: 3.13
Classifier: Programming Language :: Python :: Implementation :: CPython
Classifier: Programming Language :: Python :: Implementation :: PyPy
Requires-Python: >=3.10
Requires-Dist: cattrs~=25.1.1
Requires-Dist: falcon~=4.0.0
Requires-Dist: gunicorn~=23.0.0
Requires-Dist: jinja2~=3.1.0
Requires-Dist: tomli~=2.1.0
Requires-Dist: typing-extensions~=4.12.2
